latentcor/__init__.py
latentcor/ipol_10.xz
latentcor/ipol_11.xz
latentcor/ipol_20.xz
latentcor/ipol_21.xz
latentcor/ipol_22.xz
latentcor/ipol_30.xz
latentcor/ipol_31.xz
latentcor/ipol_32.xz
latentcor/ipol_33.xz
latentcor/latentcor.py
latentcor-0.2.5.dist-info/AUTHORS.rst
latentcor-0.2.5.dist-info/LICENSE
latentcor-0.2.5.dist-info/METADATA
latentcor-0.2.5.dist-info/WHEEL
latentcor-0.2.5.dist-info/top_level.txt
latentcor-0.2.5.dist-info/RECORD
