Metadata-Version: 2.1
Name: latentcor
Version: 0.2.5
Summary: Fast Computation of Latent Correlations for Mixed Data
Home-page: https://github.com/mingzehuang/latentcor_py
Author: Mingze Huang, Christian L. Müller, Irina Gaynanova
Author-email: mingzehuang@gmail.com, christian.mueller@stat.uni-muenchen.de, irinag@stat.tamu.edu
License: GNU General Public License v3
Keywords: latentcor
Classifier: Development Status :: 2 - Pre-Alpha
Classifier: Intended Audience :: Developers
Classifier: License :: OSI Approved :: GNU General Public License v3 (GPLv3)
Classifier: Natural Language :: English
Classifier: Programming Language :: Python :: 3
Classifier: Programming Language :: Python :: 3.7
Classifier: Programming Language :: Python :: 3.8
Classifier: Programming Language :: Python :: 3.9
Classifier: Programming Language :: Python :: 3.10
Requires-Python: >=3.7
License-File: LICENSE
License-File: AUTHORS.rst
Requires-Dist: numpy >=1.21
Requires-Dist: scipy >=1.7
Requires-Dist: statsmodels >=0.13
Requires-Dist: seaborn >=0.11
Requires-Dist: matplotlib >=3.5
Requires-Dist: joblib >=1.1
